graph_sc/__init__.py
graph_sc/models.py
graph_sc/my_test.py
graph_sc/train.py
graph_sc/data/worm_neuron_cell.h5
graph_sc-0.0.3.dist-info/LICENSE
graph_sc-0.0.3.dist-info/METADATA
graph_sc-0.0.3.dist-info/WHEEL
graph_sc-0.0.3.dist-info/top_level.txt
graph_sc-0.0.3.dist-info/RECORD
