Metadata-Version: 2.1
Name: graph-sc
Version: 0.0.3
Summary: Graph-sc
Home-page: UNKNOWN
Author-email: ciortanmadalina@gmail.com
License: UNKNOWN
Platform: UNKNOWN
Requires-Python: >=3.6
License-File: LICENSE
Requires-Dist: setuptools (==45.0.0)
Requires-Dist: torch
Requires-Dist: scanpy (==1.5.1)
Requires-Dist: attrdict (==2.0.1)
Requires-Dist: h5py (==3.2.1)
Requires-Dist: scipy (==1.6.0)
Requires-Dist: jgraph (==0.2.1)
Requires-Dist: louvain (==0.7.0)
Requires-Dist: openpyxl (==3.0.7)
Requires-Dist: pandas (==1.2.1)
Requires-Dist: dgl (==0.5.3)
Requires-Dist: scikit-learn (==0.22.2.post1)
Requires-Dist: xlrd (==1.2.0)
Requires-Dist: matplotlib
Requires-Dist: tqdm
Requires-Dist: leidenalg
